{
  "function": "Si",
  "description": "内向的感覚: 記憶・既知の詳細・一貫性・伝統・積み重ね",
  "prototypes": [
    { "text": "以前同じような状況でこう対処したのを覚えてる" },
    { "text": "手順通りにやる方が結局速い" },
    { "text": "去年の今頃、同じこと心配してた日記を見返した" },
    { "text": "料理は分量きっちり計らないと落ち着かない" },
    { "text": "学生時代の先生の言葉が、今でもふと戻ってくる" },
    { "text": "データの前例を見てから判断したい" },
    { "text": "使い慣れた道具の方が結果が安定する" },
    { "text": "馴染みのカフェが一番仕事がはかどる" },
    { "text": "新しいのを試すより、検証済みの方法を深めたい" },
    { "text": "ノートは必ず同じブランドと太さで揃える" },
    { "text": "昔のメモを読み返すと、けっこう今も通用する" },
    { "text": "朝のルーチンが崩れると 1 日が引きずる" },
    { "text": "実家の料理の味は、どこのレストランにも出せない" },
    { "text": "職場の引き出しの配置、3 年変わってない" },
    { "text": "あの曲を聴くと、高校の夏の匂いまで蘇る" },
    { "text": "記録を残す癖は、後で何度も自分を助ける" },
    { "text": "過去のプロジェクトと状況が似てる、ログを漁ろう" },
    { "text": "昔からやってるやり方を、理由まで説明できる" },
    { "text": "急な変更より、段階的な改善の方が信頼できる" },
    { "text": "伝統的な作法にはちゃんと理由があるものが多い" },
    { "text": "毎日同じ時間に同じ場所を歩く心地よさ" },
    { "text": "数値で示せる実績より、積み上げた時間を信じる" },
    { "text": "去年のノートから今年のヒントが出てきた" },
    { "text": "「前例あり」と聞くと安心する自分がいる" },
    { "text": "1 年経つと、同じ季節の匂いでその時を思い出す" }
  ]
}
